esloco/__init__.py
esloco/bed_operations.py
esloco/combined_calculations.py
esloco/config_handler.py
esloco/counting.py
esloco/coverage.py
esloco/create_insertion_genome.py
esloco/esloco.py
esloco/fasta_operations.py
esloco/genome_generation.py
esloco/plot_esloco.py
esloco/plot_functions.py
esloco/read_operations.py
esloco/utils.py
esloco-1.0.5.dist-info/licenses/LICENSE
esloco-1.0.5.dist-info/METADATA
esloco-1.0.5.dist-info/WHEEL
esloco-1.0.5.dist-info/entry_points.txt
esloco-1.0.5.dist-info/top_level.txt
esloco-1.0.5.dist-info/RECORD
