Metadata-Version: 2.4
Name: esloco
Version: 1.0.5
Summary: Estimating Long-Read Coverage for Whole-Genome Sequencing
Author: aweich
Project-URL: Repository, https://github.com/aweich/esloco.git
Classifier: Programming Language :: Python :: 3
Classifier: Operating System :: OS Independent
Requires-Python: >=3.9
License-File: LICENSE
Requires-Dist: biopython
Requires-Dist: numpy
Requires-Dist: pandas
Requires-Dist: joblib
Requires-Dist: tqdm_joblib
Requires-Dist: psutil
Requires-Dist: matplotlib
Requires-Dist: seaborn
Requires-Dist: scipy
Requires-Dist: plotly
Requires-Dist: pyfiglet
Requires-Dist: kaleido<1.0.0
Dynamic: license-file
